{
    "syntactic": [
        "speech quality",
        "university",
        "speaker adaptation",
        "mathematics"
    ],
    "semantic": [
        "speech signals",
        "speech quality",
        "speaker adaptation",
        "university",
        "mathematics"
    ],
    "union": [
        "university",
        "speech signals",
        "mathematics",
        "speech quality",
        "speaker adaptation"
    ],
    "enhanced": [
        "education",
        "speech communication",
        "speech enhancement",
        "hidden markov models",
        "hidden markov model (hmm)",
        "linguistics",
        "signal to noise ratio",
        "markov processes",
        "signal processing",
        "correlation analysis",
        "engineering"
    ],
    "explanation": {
        "speech quality": [
            "speech quality"
        ],
        "speaker adaptation": [
            "speaker adaptation"
        ],
        "university": [
            "university",
            "department university",
            "department"
        ],
        "mathematics": [
            "speaker adaptation",
            "mathematics"
        ],
        "speech signals": [
            "speech path",
            "text speech",
            "speech",
            "reference speech",
            "speaker speech",
            "term speech",
            "end speech"
        ],
        "education": [
            "university",
            "department university",
            "department"
        ],
        "speech communication": [
            "speech path",
            "text speech",
            "speech quality",
            "speaker adaptation",
            "speech",
            "reference speech",
            "speaker speech",
            "term speech",
            "end speech"
        ],
        "speech enhancement": [
            "speech quality"
        ],
        "hidden markov models": [
            "speaker adaptation"
        ],
        "hidden markov model (hmm)": [
            "speaker adaptation"
        ],
        "linguistics": [
            "speech path",
            "text speech",
            "speech quality",
            "speaker adaptation",
            "speech",
            "reference speech",
            "speaker speech",
            "term speech",
            "end speech"
        ],
        "signal to noise ratio": [
            "speech quality"
        ],
        "markov processes": [
            "speaker adaptation"
        ],
        "signal processing": [
            "speech quality"
        ],
        "correlation analysis": [
            "speaker adaptation"
        ],
        "engineering": [
            "speech quality"
        ]
    }
}