{
    "syntactic": [
        "botnets"
    ],
    "semantic": [
        "malicious activities",
        "malwares",
        "layered",
        "botnets",
        "vision systems"
    ],
    "union": [
        "malwares",
        "layered",
        "malicious activities",
        "botnets",
        "vision systems"
    ],
    "enhanced": [
        "operating systems",
        "computer crime",
        "network security",
        "software architecture patterns",
        "intrusion detection",
        "robots",
        "computer vision",
        "computer science",
        "security of data",
        "cryptography",
        "computer networks",
        "software architecture",
        "robotics",
        "computer imaging and vision",
        "computer security",
        "cryptology",
        "software design",
        "software engineering"
    ],
    "explanation": {
        "botnets": [
            "botnet",
            "botnet botnet"
        ],
        "malwares": [
            "botnet",
            "botnet botnet"
        ],
        "malicious activities": [
            "botnet",
            "botnet botnet"
        ],
        "vision systems": [
            "vision"
        ],
        "layered": [
            "layer"
        ],
        "operating systems": [
            "botnet",
            "botnet botnet"
        ],
        "computer crime": [
            "botnet",
            "botnet botnet"
        ],
        "network security": [
            "botnet",
            "botnet botnet"
        ],
        "software architecture patterns": [
            "layer"
        ],
        "intrusion detection": [
            "botnet",
            "botnet botnet"
        ],
        "robots": [
            "vision"
        ],
        "computer vision": [
            "vision"
        ],
        "computer science": [
            "vision",
            "botnet botnet",
            "botnet",
            "layer"
        ],
        "security of data": [
            "botnet",
            "botnet botnet"
        ],
        "cryptography": [
            "botnet",
            "botnet botnet"
        ],
        "computer networks": [
            "botnet",
            "botnet botnet"
        ],
        "software architecture": [
            "layer"
        ],
        "robotics": [
            "vision"
        ],
        "computer imaging and vision": [
            "vision"
        ],
        "computer security": [
            "botnet",
            "botnet botnet"
        ],
        "cryptology": [
            "botnet",
            "botnet botnet"
        ],
        "software design": [
            "layer"
        ],
        "software engineering": [
            "layer"
        ]
    }
}