{
    "syntactic": [],
    "semantic": [
        "classification models",
        "automatic classification",
        "supervised classification",
        "classification methods"
    ],
    "union": [
        "classification models",
        "automatic classification",
        "supervised classification",
        "classification methods"
    ],
    "enhanced": [
        "image classification",
        "computer systems",
        "imaging systems",
        "computer science",
        "image reconstruction",
        "image analysis",
        "image processing",
        "computer imaging and vision"
    ],
    "explanation": {
        "classification models": [
            "loss classification",
            "bias classification",
            "baseline classification",
            "classification",
            "png classification"
        ],
        "supervised classification": [
            "classification"
        ],
        "classification methods": [
            "loss classification",
            "png classification",
            "bias classification",
            "classification",
            "baseline classification"
        ],
        "automatic classification": [
            "classification"
        ],
        "image classification": [
            "classification"
        ],
        "computer systems": [
            "loss classification",
            "classification",
            "bias classification",
            "baseline classification",
            "png classification"
        ],
        "imaging systems": [
            "classification"
        ],
        "computer science": [
            "loss classification",
            "classification",
            "bias classification",
            "baseline classification",
            "png classification"
        ],
        "image reconstruction": [
            "classification"
        ],
        "image analysis": [
            "classification"
        ],
        "image processing": [
            "classification"
        ],
        "computer imaging and vision": [
            "classification"
        ]
    }
}