{
    "syntactic": [
        "gpu",
        "engine",
        "quantization",
        "optimization",
        "acceleration sensors",
        "visualization",
        "gpus",
        "cloud storage"
    ],
    "semantic": [
        "cloud services",
        "quantization",
        "engine",
        "optimization",
        "gpus",
        "cloud storage"
    ],
    "union": [
        "cloud services",
        "gpu",
        "quantization",
        "optimization",
        "engine",
        "acceleration sensors",
        "visualization",
        "gpus",
        "cloud storage"
    ],
    "enhanced": [
        "distributed database systems",
        "commerce",
        "cloud providers",
        "mobile devices",
        "computing paradigm",
        "computing resource",
        "computing environments",
        "software as a service",
        "communication",
        "program processors",
        "image compression",
        "signal processing",
        "mathematics",
        "engineering",
        "accelerometers",
        "human computer interaction",
        "cuda",
        "digital storage",
        "cloud computing",
        "data communication systems",
        "parallel processing systems",
        "query languages",
        "economics",
        "virtual machines",
        "virtualizations",
        "grid computing",
        "mobile computing",
        "microprocessor chips",
        "image quality",
        "image coding",
        "sensors",
        "computer science",
        "parallel programming",
        "graphics processing unit",
        "computer hardware",
        "computer systems",
        "distributed systems",
        "database systems",
        "wireless telecommunication systems",
        "telecommunication networks",
        "image analysis",
        "image processing",
        "parallel algorithms",
        "parallel architectures",
        "computer programming languages",
        "distributed computer systems",
        "computer networks",
        "communication systems",
        "telecommunication systems",
        "computer imaging and vision",
        "computer programming"
    ],
    "explanation": {
        "acceleration sensors": [
            "acceleration tensor"
        ],
        "cloud storage": [
            "cloud storage"
        ],
        "gpus": [
            "gpus"
        ],
        "optimization": [
            "optimization"
        ],
        "engine": [
            "engine"
        ],
        "quantization": [
            "quantization"
        ],
        "gpu": [
            "gpu",
            "gpus"
        ],
        "visualization": [
            "visualization"
        ],
        "cloud services": [
            "cloud tpus",
            "research cloud",
            "cloud",
            "support cloud",
            "google cloud",
            "cloud trc",
            "cloud tpu"
        ],
        "distributed database systems": [
            "cloud tpus",
            "research cloud",
            "cloud",
            "support cloud",
            "google cloud",
            "cloud trc",
            "cloud tpu"
        ],
        "commerce": [
            "cloud tpus",
            "research cloud",
            "cloud",
            "support cloud",
            "google cloud",
            "cloud trc",
            "cloud tpu"
        ],
        "cloud providers": [
            "cloud tpus",
            "research cloud",
            "cloud",
            "support cloud",
            "google cloud",
            "cloud trc",
            "cloud tpu"
        ],
        "mobile devices": [
            "cloud tpus",
            "research cloud",
            "cloud",
            "support cloud",
            "google cloud",
            "cloud trc",
            "cloud tpu"
        ],
        "computing paradigm": [
            "cloud tpus",
            "research cloud",
            "cloud",
            "support cloud",
            "google cloud",
            "cloud trc",
            "cloud tpu"
        ],
        "computing resource": [
            "cloud tpus",
            "research cloud",
            "cloud",
            "support cloud",
            "google cloud",
            "cloud trc",
            "cloud tpu"
        ],
        "computing environments": [
            "cloud tpus",
            "research cloud",
            "cloud",
            "support cloud",
            "google cloud",
            "cloud trc",
            "cloud tpu"
        ],
        "software as a service": [
            "cloud tpus",
            "research cloud",
            "cloud",
            "support cloud",
            "google cloud",
            "cloud trc",
            "cloud tpu"
        ],
        "communication": [
            "cloud tpus",
            "research cloud",
            "cloud",
            "support cloud",
            "google cloud",
            "cloud trc",
            "cloud tpu"
        ],
        "program processors": [
            "gpu",
            "gpus"
        ],
        "image compression": [
            "quantization"
        ],
        "signal processing": [
            "quantization"
        ],
        "mathematics": [
            "optimization"
        ],
        "engineering": [
            "engine",
            "quantization"
        ],
        "accelerometers": [
            "acceleration tensor"
        ],
        "human computer interaction": [
            "visualization"
        ],
        "cuda": [
            "gpus"
        ],
        "digital storage": [
            "cloud storage"
        ],
        "cloud computing": [
            "research cloud",
            "google cloud",
            "cloud tpus",
            "cloud tpu",
            "cloud",
            "support cloud",
            "cloud trc",
            "cloud storage"
        ],
        "data communication systems": [
            "research cloud",
            "google cloud",
            "cloud tpus",
            "cloud tpu",
            "cloud",
            "support cloud",
            "cloud trc"
        ],
        "parallel processing systems": [
            "gpu",
            "research cloud",
            "google cloud",
            "cloud tpus",
            "cloud tpu",
            "cloud",
            "support cloud",
            "gpus",
            "cloud trc"
        ],
        "query languages": [
            "research cloud",
            "google cloud",
            "cloud tpus",
            "cloud tpu",
            "cloud",
            "support cloud",
            "cloud trc"
        ],
        "economics": [
            "research cloud",
            "google cloud",
            "cloud tpus",
            "cloud tpu",
            "cloud",
            "support cloud",
            "cloud trc"
        ],
        "virtual machines": [
            "research cloud",
            "google cloud",
            "cloud tpus",
            "cloud tpu",
            "cloud",
            "support cloud",
            "cloud trc"
        ],
        "virtualizations": [
            "research cloud",
            "google cloud",
            "cloud tpus",
            "cloud tpu",
            "cloud",
            "support cloud",
            "cloud trc"
        ],
        "grid computing": [
            "research cloud",
            "google cloud",
            "cloud tpus",
            "cloud tpu",
            "cloud",
            "support cloud",
            "cloud trc"
        ],
        "mobile computing": [
            "research cloud",
            "google cloud",
            "cloud tpus",
            "cloud tpu",
            "cloud",
            "support cloud",
            "cloud trc"
        ],
        "microprocessor chips": [
            "gpu",
            "gpus"
        ],
        "image quality": [
            "quantization"
        ],
        "image coding": [
            "quantization"
        ],
        "sensors": [
            "acceleration tensor"
        ],
        "computer science": [
            "research cloud",
            "quantization",
            "visualization",
            "cloud",
            "cloud tpu",
            "cloud trc",
            "acceleration tensor",
            "gpu",
            "google cloud",
            "cloud tpus",
            "support cloud",
            "gpus",
            "cloud storage"
        ],
        "parallel programming": [
            "gpus"
        ],
        "graphics processing unit": [
            "gpus"
        ],
        "computer hardware": [
            "acceleration tensor",
            "gpu",
            "gpus",
            "cloud storage"
        ],
        "computer systems": [
            "gpu",
            "research cloud",
            "google cloud",
            "cloud tpus",
            "cloud tpu",
            "cloud",
            "support cloud",
            "gpus",
            "cloud trc",
            "cloud storage"
        ],
        "distributed systems": [
            "gpu",
            "research cloud",
            "google cloud",
            "cloud tpus",
            "cloud tpu",
            "cloud",
            "support cloud",
            "gpus",
            "cloud trc"
        ],
        "database systems": [
            "research cloud",
            "google cloud",
            "cloud tpus",
            "cloud tpu",
            "cloud",
            "support cloud",
            "cloud trc"
        ],
        "wireless telecommunication systems": [
            "research cloud",
            "google cloud",
            "cloud tpus",
            "cloud tpu",
            "cloud",
            "support cloud",
            "cloud trc"
        ],
        "telecommunication networks": [
            "research cloud",
            "google cloud",
            "cloud tpus",
            "cloud tpu",
            "cloud",
            "support cloud",
            "cloud trc"
        ],
        "image analysis": [
            "quantization"
        ],
        "image processing": [
            "quantization"
        ],
        "parallel algorithms": [
            "gpus"
        ],
        "parallel architectures": [
            "gpus"
        ],
        "computer programming languages": [
            "gpus"
        ],
        "distributed computer systems": [
            "gpu",
            "research cloud",
            "google cloud",
            "cloud tpus",
            "cloud",
            "gpus",
            "support cloud",
            "cloud trc",
            "cloud tpu"
        ],
        "computer networks": [
            "research cloud",
            "google cloud",
            "cloud tpus",
            "cloud tpu",
            "cloud",
            "support cloud",
            "cloud trc"
        ],
        "communication systems": [
            "research cloud",
            "google cloud",
            "cloud tpus",
            "cloud tpu",
            "cloud",
            "support cloud",
            "cloud trc"
        ],
        "telecommunication systems": [
            "research cloud",
            "google cloud",
            "cloud tpus",
            "cloud tpu",
            "cloud",
            "support cloud",
            "cloud trc"
        ],
        "computer imaging and vision": [
            "quantization"
        ],
        "computer programming": [
            "gpus"
        ]
    }
}