{
  "arxivLinks": {
    "confidence": [
      1.0
    ],
    "excerpt": [
      "https://arxiv.org/abs/1603.06937",
      "https://arxiv.org/abs/2002.11098",
      "https://arxiv.org/abs/1603.06937, 2016.\n  2. A. Bulat, J. Kossaifi, G. Tzimiropoulos, M. Pantic, **Toward Fast and Accurate Human Pose Estimation via Soft-Gated Skip Connections**, https://arxiv.org/abs/2002.11098, 2020.\n\n\n",
      "https://arxiv.org/abs/2002.11098, 2020.\n\n\n"
    ],
    "technique": "Regular expression"
  },
  "citation": [
    {
      "confidence": [
        1
      ],
      "excerpt": "  1. A. Newell, K.Yang, J. Deng, **Stacked Hourglass Networks for Human Pose Estimation**, arXiv:1603.06937, 2016.\n  2. A. Bulat, J. Kossaifi, G. Tzimiropoulos, M. Pantic, **Toward Fast and Accurate Human Pose Estimation via Soft-Gated Skip Connections**, arXiv:2002.11098, 2020.\n\n\n\n",
      "technique": "Header extraction"
    }
  ],
  "codeRepository": {
    "confidence": [
      1.0
    ],
    "excerpt": "https://github.com/salinasJJ/BBpose",
    "technique": "GitHub API"
  },
  "dateCreated": {
    "confidence": [
      1.0
    ],
    "excerpt": "2021-07-07T02:28:37Z",
    "technique": "GitHub API"
  },
  "dateModified": {
    "confidence": [
      1.0
    ],
    "excerpt": "2021-12-09T11:55:31Z",
    "technique": "GitHub API"
  },
  "description": [
    {
      "confidence": [
        0.9602578228589613
      ],
      "excerpt": "BB-Pose is a Tensorflow 2 training pipeline for human pose estimation. The aim of this codebase is to set up a foundation on which future projects might be able to build upon. Supported models currently include: \n",
      "technique": "Supervised classification"
    },
    {
      "confidence": [
        0.8112760226377446
      ],
      "excerpt": "Supported datasets currently include: \n",
      "technique": "Supervised classification"
    },
    {
      "confidence": [
        0.9587934904968554
      ],
      "excerpt": "This project is setup around a config file which contains numerous adjustable parameters. Any changes to how the project runs must be done here by updating the params. There are 3 main commands to update the params: \n",
      "technique": "Supervised classification"
    },
    {
      "confidence": [
        0.9205365267542809
      ],
      "excerpt": "  3. The 'force' command is a special command that will update a set of model-defined hidden params. The command is there for a specific use case (i.e. resetting hidden params after an accidental updating) but in general, users of this repository should never have to use this command. \n",
      "technique": "Supervised classification"
    },
    {
      "confidence": [
        0.850767596525648,
        0.8749225644934449
      ],
      "excerpt": "Note #1: The 'reset' command will clear out all user-defined values as well as those of the hidden params. Without these pre-defined params, the model will fail to work properly, if at all. Please use this command carefully. \nNote #2: CHECK VERSION NUMBER! Users should get into the practice of always checking which version number is being set in order to avoid overwriting old models. \n",
      "technique": "Supervised classification"
    },
    {
      "confidence": [
        0.9935228225061342
      ],
      "excerpt": "There are many params, some of which are interconnected to one another, and some which have limitations. Please see Glossary for a full breakdown of all these params. \n",
      "technique": "Supervised classification"
    },
    {
      "confidence": [
        0.8633058778255138,
        0.8151825155522063
      ],
      "excerpt": "  1. setup: retrieves required data files and prepares the data for downloading. \n  2. generate: downloads the image set and generates Tensorflow datasets. \n",
      "technique": "Supervised classification"
    },
    {
      "confidence": [
        1.0
      ],
      "excerpt": "Human Pose Estimation using Soft-gated Skip Connection and base Hourglass Networks. Implemented in Tensorflow 2.",
      "technique": "GitHub API"
    }
  ],
  "downloadUrl": {
    "confidence": [
      1.0
    ],
    "excerpt": "https://github.com/BB-Repos/BBpose/releases",
    "technique": "GitHub API"
  },
  "forks_count": {
    "confidence": [
      1.0
    ],
    "excerpt": {
      "count": 9,
      "date": "Mon, 27 Dec 2021 07:36:31 GMT"
    },
    "technique": "GitHub API"
  },
  "forks_url": {
    "confidence": [
      1.0
    ],
    "excerpt": "https://api.github.com/repos/salinasJJ/BBpose/forks",
    "technique": "GitHub API"
  },
  "fullName": {
    "confidence": [
      1.0
    ],
    "excerpt": "salinasJJ/BBpose",
    "technique": "GitHub API"
  },
  "hasScriptFile": {
    "confidence": [
      1.0
    ],
    "excerpt": [
      "https://raw.githubusercontent.com/BB-Repos/BBpose/main/bbpose/ingestion/scripts/data.sh"
    ],
    "technique": "File Exploration"
  },
  "installation": [
    {
      "confidence": [
        1
      ],
      "excerpt": "  1. Clone this repository:\n  ```\n  git clone https://github.com/salinasJJ/BBpose.git \n  ```\n  2. Create a virtual environment (using Pipenv or Conda for example).\n\n  3. Install the project onto your system:\n  ```\n  pip install -e BBpose\n  ```                                                               \n  4. Install dependencies:\n  ```\n  pip install -r BBpose/bbpose/requirements.txt\n  ```\n  5. Make script executable: \n  ```\n  chmod +x BBpose/bbpose/ingestion/scripts/data.sh        \n  ```\n    \n",
      "technique": "Header extraction"
    },
    {
      "confidence": [
        0.9717106327039013
      ],
      "excerpt": "    --version 0 \\ \n",
      "technique": "Supervised classification"
    },
    {
      "confidence": [
        0.8907182191520274
      ],
      "excerpt": "Note #2: CHECK VERSION NUMBER! Users should get into the practice of always checking which version number is being set in order to avoid overwriting old models. \n",
      "technique": "Supervised classification"
    }
  ],
  "invocation": [
    {
      "confidence": [
        0.8106500135224463,
        0.9333384803827206,
        0.8265814884749882,
        0.9044274896315364
      ],
      "excerpt": "  1. The 'reset' command will reset all params back to their default values: \n  python BBpose/bbpose/main.py reset     \n  2. The 'update' command will update all requested params to new values. For example:                \npython BBpose/bbpose/main.py update \\ \n",
      "technique": "Supervised classification"
    },
    {
      "confidence": [
        0.8594142235991984
      ],
      "excerpt": "    --use_records True \\ \n",
      "technique": "Supervised classification"
    },
    {
      "confidence": [
        0.9333384803827206
      ],
      "excerpt": "  python BBpose/bbpose/main.py force \\ \n",
      "technique": "Supervised classification"
    },
    {
      "confidence": [
        0.9191523614684337
      ],
      "excerpt": "python BBpose/bbpose/main.py ingest --setup --generate \n",
      "technique": "Supervised classification"
    },
    {
      "confidence": [
        0.9351965264211335
      ],
      "excerpt": "python BBpose/bbpose/main.py ingest --generate \n",
      "technique": "Supervised classification"
    },
    {
      "confidence": [
        0.956243229936475
      ],
      "excerpt": "python BBpose/bbpose/main.py train \n",
      "technique": "Supervised classification"
    },
    {
      "confidence": [
        0.956243229936475
      ],
      "excerpt": "python BBpose/bbpose/main.py train --restore \n",
      "technique": "Supervised classification"
    },
    {
      "confidence": [
        0.956999482560778
      ],
      "excerpt": "python BBpose/bbpose/main.py test \n",
      "technique": "Supervised classification"
    }
  ],
  "issueTracker": {
    "confidence": [
      1.0
    ],
    "excerpt": "https://api.github.com/repos/salinasJJ/BBpose/issues{/number}",
    "technique": "GitHub API"
  },
  "languages": {
    "confidence": [
      1.0
    ],
    "excerpt": [
      "Python",
      "Shell"
    ],
    "technique": "GitHub API"
  },
  "license": {
    "confidence": [
      1.0
    ],
    "excerpt": {
      "name": "MIT License",
      "url": "https://api.github.com/licenses/mit"
    },
    "technique": "GitHub API"
  },
  "licenseText": {
    "confidence": [
      1.0
    ],
    "excerpt": "b'MIT License\\n\\nCopyright (c) 2021 BB-Repos\\n\\nPermission is hereby granted, free of charge, to any person obtaining a copy\\nof this software and associated documentation files (the \"Software\"), to deal\\nin the Software without restriction, including without limitation the rights\\nto use, copy, modify, merge, publish, distribute, sublicense, and/or sell\\ncopies of the Software, and to permit persons to whom the Software is\\nfurnished to do so, subject to the following conditions:\\n\\nThe above copyright notice and this permission notice shall be included in all\\ncopies or substantial portions of the Software.\\n\\nTHE SOFTWARE IS PROVIDED \"AS IS\", WITHOUT WARRANTY OF ANY KIND, EXPRESS OR\\nIMPLIED, INCLUDING BUT NOT LIMITED TO THE WARRANTIES OF MERCHANTABILITY,\\nFITNESS FOR A PARTICULAR PURPOSE AND NONINFRINGEMENT. IN NO EVENT SHALL THE\\nAUTHORS OR COPYRIGHT HOLDERS BE LIABLE FOR ANY CLAIM, DAMAGES OR OTHER\\nLIABILITY, WHETHER IN AN ACTION OF CONTRACT, TORT OR OTHERWISE, ARISING FROM,\\nOUT OF OR IN CONNECTION WITH THE SOFTWARE OR THE USE OR OTHER DEALINGS IN THE\\nSOFTWARE.\\n'",
    "technique": "File Exploration"
  },
  "long_title": {
    "confidence": [
      1.0
    ],
    "excerpt": "BB-Pose",
    "technique": "Regular expression"
  },
  "name": {
    "confidence": [
      1.0
    ],
    "excerpt": "BBpose",
    "technique": "GitHub API"
  },
  "owner": {
    "confidence": [
      1.0
    ],
    "excerpt": "salinasJJ",
    "technique": "GitHub API"
  },
  "ownerType": {
    "confidence": [
      1.0
    ],
    "excerpt": "User",
    "technique": "GitHub API"
  },
  "readme_url": {
    "confidence": [
      1.0
    ],
    "excerpt": "https://github.com/salinasJJ/BBpose/blob/main/README.md",
    "technique": "GitHub API"
  },
  "stargazers_count": {
    "confidence": [
      1.0
    ],
    "excerpt": {
      "count": 12,
      "date": "Mon, 27 Dec 2021 07:36:31 GMT"
    },
    "technique": "GitHub API"
  }
}