{
  "arxivLinks": {
    "confidence": [
      1.0
    ],
    "excerpt": [
      "https://arxiv.org/abs/1703.03400"
    ],
    "technique": "Regular expression"
  },
  "citation": [
    {
      "confidence": [
        1.0
      ],
      "excerpt": "@misc{MAML_Pytorch,\n  author = {Liangqu Long},\n  title = {MAML-Pytorch Implementation},\n  year = {2018},\n  publisher = {GitHub},\n  journal = {GitHub repository},\n  howpublished = {\\url{https://github.com/dragen1860/MAML-Pytorch}},\n  commit = {master}\n}",
      "technique": "Regular expression"
    }
  ],
  "codeRepository": {
    "confidence": [
      1.0
    ],
    "excerpt": "https://github.com/dragen1860/MAML-Pytorch",
    "technique": "GitHub API"
  },
  "dateCreated": {
    "confidence": [
      1.0
    ],
    "excerpt": "2018-02-01T14:19:54Z",
    "technique": "GitHub API"
  },
  "dateModified": {
    "confidence": [
      1.0
    ],
    "excerpt": "2021-12-20T05:04:52Z",
    "technique": "GitHub API"
  },
  "description": [
    {
      "confidence": [
        0.8985320961252093,
        0.8864184287814117
      ],
      "excerpt": "PyTorch implementation of the supervised learning experiments from the paper: \nModel-Agnostic Meta-Learning (MAML). \n",
      "technique": "Supervised classification"
    },
    {
      "confidence": [
        0.8070943746187048
      ],
      "excerpt": "For Tensorflow Implementation, please visit official HERE and simplier version HERE. \n",
      "technique": "Supervised classification"
    },
    {
      "confidence": [
        0.8740375537320283
      ],
      "excerpt": "and the performance below is true and achieved on my machine. \n",
      "technique": "Supervised classification"
    },
    {
      "confidence": [
        1.0
      ],
      "excerpt": "Elegant PyTorch implementation of paper Model-Agnostic Meta-Learning (MAML)",
      "technique": "GitHub API"
    }
  ],
  "downloadUrl": {
    "confidence": [
      1.0
    ],
    "excerpt": "https://github.com/dragen1860/MAML-Pytorch/releases",
    "technique": "GitHub API"
  },
  "forks_count": {
    "confidence": [
      1.0
    ],
    "excerpt": {
      "count": 327,
      "date": "Tue, 21 Dec 2021 10:21:38 GMT"
    },
    "technique": "GitHub API"
  },
  "forks_url": {
    "confidence": [
      1.0
    ],
    "excerpt": "https://api.github.com/repos/dragen1860/MAML-Pytorch/forks",
    "technique": "GitHub API"
  },
  "fullName": {
    "confidence": [
      1.0
    ],
    "excerpt": "dragen1860/MAML-Pytorch",
    "technique": "GitHub API"
  },
  "installation": [
    {
      "confidence": [
        0.8837680365796365,
        0.9322609392449874,
        0.834903696847977
      ],
      "excerpt": "python: 3.x \nPytorch: 0.4+ \nFor 5-way 1-shot exp., it allocates nearly 6GB GPU memory. \n",
      "technique": "Supervised classification"
    }
  ],
  "invocation": [
    {
      "confidence": [
        0.9326397734481552
      ],
      "excerpt": "download MiniImagenet dataset from here, splitting: train/val/test.csv from here. \n",
      "technique": "Supervised classification"
    },
    {
      "confidence": [
        0.8639986685036579,
        0.8639986685036579
      ],
      "excerpt": "    \u251c\u2500\u2500 n0210891500001298.jpg \n    \u251c\u2500\u2500 n0287152500001298.jpg  \n",
      "technique": "Supervised classification"
    },
    {
      "confidence": [
        0.8916366759154853
      ],
      "excerpt": "\u251c\u2500\u2500 test.csv \n",
      "technique": "Supervised classification"
    },
    {
      "confidence": [
        0.8897107595245954,
        0.8580692258218791
      ],
      "excerpt": "\u2514\u2500\u2500 train.csv \n3. modify the `path` in `miniimagenet_train.py`:python \n",
      "technique": "Supervised classification"
    },
    {
      "confidence": [
        0.8438769870689441
      ],
      "excerpt": "        mini_test = MiniImagenet('miniimagenet/', mode='test', n_way=args.n_way, k_shot=args.k_spt, \n",
      "technique": "Supervised classification"
    },
    {
      "confidence": [
        0.8586566369574141
      ],
      "excerpt": "just run python miniimagenet_train.py and the running screenshot is as follows: \n",
      "technique": "Supervised classification"
    },
    {
      "confidence": [
        0.9128805350806559
      ],
      "excerpt": "run python omniglot_train.py, the program will download omniglot dataset automatically. \n",
      "technique": "Supervised classification"
    }
  ],
  "issueTracker": {
    "confidence": [
      1.0
    ],
    "excerpt": "https://api.github.com/repos/dragen1860/MAML-Pytorch/issues{/number}",
    "technique": "GitHub API"
  },
  "languages": {
    "confidence": [
      1.0
    ],
    "excerpt": [
      "Python"
    ],
    "technique": "GitHub API"
  },
  "license": {
    "confidence": [
      1.0
    ],
    "excerpt": {
      "name": "MIT License",
      "url": "https://api.github.com/licenses/mit"
    },
    "technique": "GitHub API"
  },
  "licenseText": {
    "confidence": [
      1.0
    ],
    "excerpt": "b'MIT License\\n\\nCopyright (c) 2019 Jackie Loong\\n\\nPermission is hereby granted, free of charge, to any person obtaining a copy\\nof this software and associated documentation files (the \"Software\"), to deal\\nin the Software without restriction, including without limitation the rights\\nto use, copy, modify, merge, publish, distribute, sublicense, and/or sell\\ncopies of the Software, and to permit persons to whom the Software is\\nfurnished to do so, subject to the following conditions:\\n\\nThe above copyright notice and this permission notice shall be included in all\\ncopies or substantial portions of the Software.\\n\\nTHE SOFTWARE IS PROVIDED \"AS IS\", WITHOUT WARRANTY OF ANY KIND, EXPRESS OR\\nIMPLIED, INCLUDING BUT NOT LIMITED TO THE WARRANTIES OF MERCHANTABILITY,\\nFITNESS FOR A PARTICULAR PURPOSE AND NONINFRINGEMENT. IN NO EVENT SHALL THE\\nAUTHORS OR COPYRIGHT HOLDERS BE LIABLE FOR ANY CLAIM, DAMAGES OR OTHER\\nLIABILITY, WHETHER IN AN ACTION OF CONTRACT, TORT OR OTHERWISE, ARISING FROM,\\nOUT OF OR IN CONNECTION WITH THE SOFTWARE OR THE USE OR OTHER DEALINGS IN THE\\nSOFTWARE.\\n'",
    "technique": "File Exploration"
  },
  "long_title": {
    "confidence": [
      1.0
    ],
    "excerpt": "MAML-Pytorch",
    "technique": "Regular expression"
  },
  "name": {
    "confidence": [
      1.0
    ],
    "excerpt": "MAML-Pytorch",
    "technique": "GitHub API"
  },
  "owner": {
    "confidence": [
      1.0
    ],
    "excerpt": "dragen1860",
    "technique": "GitHub API"
  },
  "ownerType": {
    "confidence": [
      1.0
    ],
    "excerpt": "User",
    "technique": "GitHub API"
  },
  "readme_url": {
    "confidence": [
      1.0
    ],
    "excerpt": "https://github.com/dragen1860/MAML-Pytorch/blob/master/README.md",
    "technique": "GitHub API"
  },
  "stargazers_count": {
    "confidence": [
      1.0
    ],
    "excerpt": {
      "count": 1538,
      "date": "Tue, 21 Dec 2021 10:21:38 GMT"
    },
    "technique": "GitHub API"
  }
}