{
  "citation": [
    {
      "confidence": [
        1
      ],
      "excerpt": "[google tensorflow-tensorflow](https://github.com/tensorflow/tensorflow).\n[google tensorflow-compression](https://github.com/tensorflow/compression).\n[google tensorflow-models](https://github.com/tensorflow/models).\n\n[NickJohnston-google Research](https://github.com/nmjohn).\n[George Toderici-google Research](https://github.com/gtoderici)\n\n",
      "technique": "Header extraction"
    },
    {
      "confidence": [
        0.8550101043698384
      ],
      "excerpt": "|10 | 1.375 | 17.4:1| \n",
      "technique": "Supervised classification"
    }
  ],
  "codeRepository": {
    "confidence": [
      1.0
    ],
    "excerpt": "https://github.com/edmontdants/RNN-LSTM-GRU_Tensorflow-HybridModel-ResidualGRUResNet-Toderici17-CVPR",
    "technique": "GitHub API"
  },
  "contact": [
    {
      "confidence": [
        1
      ],
      "excerpt": "Model repository maintained by Nick Johnston ([NickJohnston-google](https://github.com/nmjohn)).\n",
      "technique": "Header extraction"
    }
  ],
  "dateCreated": {
    "confidence": [
      1.0
    ],
    "excerpt": "2021-04-07T23:59:19Z",
    "technique": "GitHub API"
  },
  "dateModified": {
    "confidence": [
      1.0
    ],
    "excerpt": "2021-06-28T03:25:25Z",
    "technique": "GitHub API"
  },
  "description": [
    {
      "confidence": [
        0.9614235206416658,
        0.9889147342181691
      ],
      "excerpt": "Iteration 8 without entropy coding... guess which one is the original and which is the compressed!!! \nThis is a TensorFlow model for compressing and \n",
      "technique": "Supervised classification"
    },
    {
      "confidence": [
        0.9881384603413806
      ],
      "excerpt": "in Full Resolution Image Compression with Recurrent Neural Networks. Please consult the paper for more details \n",
      "technique": "Supervised classification"
    },
    {
      "confidence": [
        0.9787841454432251
      ],
      "excerpt": "doesn't currently contain the Entropy Coding portions of our paper. \n",
      "technique": "Supervised classification"
    },
    {
      "confidence": [
        0.9419534886023793
      ],
      "excerpt": "height and width in pixels by a multiple of 32. There is an image in this folder \n",
      "technique": "Supervised classification"
    },
    {
      "confidence": [
        0.9246825623897995,
        0.9470736810220796
      ],
      "excerpt": "rely on TensorFlow's built in decoding ops, which support only PNG and JPEG at \ntime of release. \n",
      "technique": "Supervised classification"
    },
    {
      "confidence": [
        0.8977715642036982
      ],
      "excerpt": "The iteration parameter specifies the lossy-quality to target for compression. \n",
      "technique": "Supervised classification"
    },
    {
      "confidence": [
        0.8905294773892087
      ],
      "excerpt": "pixel) bpp and every increment results in an additional 1/8 bpp. \n",
      "technique": "Supervised classification"
    },
    {
      "confidence": [
        0.9518454841676348,
        0.9639786011237553
      ],
      "excerpt": "Entropy Coder: Lossless compression of the binary representation. \nAfter generating codes for an image, the lossy reconstructions for that image \n",
      "technique": "Supervised classification"
    },
    {
      "confidence": [
        0.8186466195300663,
        0.8378804680069545
      ],
      "excerpt": "One of the primary metrics for comparing how similar two images are \nis MS-SSIM. \n",
      "technique": "Supervised classification"
    },
    {
      "confidence": [
        1.0
      ],
      "excerpt": "end-to-end learned based High Image Compression ratio for paper Full-Resolution Lossy Image Compression CVPR17",
      "technique": "GitHub API"
    }
  ],
  "downloadUrl": {
    "confidence": [
      1.0
    ],
    "excerpt": "https://github.com/edmontdants/RNN-LSTM-GRU_Tensorflow-Hybrid-Model-Residual-GRU-ResNet-Toderici2017-CVPR/releases",
    "technique": "GitHub API"
  },
  "forks_count": {
    "confidence": [
      1.0
    ],
    "excerpt": {
      "count": 0,
      "date": "Thu, 23 Dec 2021 16:32:57 GMT"
    },
    "technique": "GitHub API"
  },
  "forks_url": {
    "confidence": [
      1.0
    ],
    "excerpt": "https://api.github.com/repos/edmontdants/RNN-LSTM-GRU_Tensorflow-HybridModel-ResidualGRUResNet-Toderici17-CVPR/forks",
    "technique": "GitHub API"
  },
  "fullName": {
    "confidence": [
      1.0
    ],
    "excerpt": "edmontdants/RNN-LSTM-GRU_Tensorflow-HybridModel-ResidualGRUResNet-Toderici17-CVPR",
    "technique": "GitHub API"
  },
  "invocation": [
    {
      "confidence": [
        0.8378770472276811
      ],
      "excerpt": "python encoder.py --input_image=/your/image/here.png \n",
      "technique": "Supervised classification"
    },
    {
      "confidence": [
        0.8111822740982727
      ],
      "excerpt": "The output_codes file contains the numpy shape and a flattened, bit-packed \n",
      "technique": "Supervised classification"
    },
    {
      "confidence": [
        0.8407893028668304
      ],
      "excerpt": "python msssim.py --original_image=/path/to/your/image.png \n",
      "technique": "Supervised classification"
    }
  ],
  "issueTracker": {
    "confidence": [
      1.0
    ],
    "excerpt": "https://api.github.com/repos/edmontdants/RNN-LSTM-GRU_Tensorflow-HybridModel-ResidualGRUResNet-Toderici17-CVPR/issues{/number}",
    "technique": "GitHub API"
  },
  "languages": {
    "confidence": [
      1.0
    ],
    "excerpt": [
      "Python"
    ],
    "technique": "GitHub API"
  },
  "license": {
    "confidence": [
      1.0
    ],
    "technique": "GitHub API"
  },
  "long_title": {
    "confidence": [
      1.0
    ],
    "excerpt": "### Full Resolution Image Compression with Recurrent Neural Networks",
    "technique": "Regular expression"
  },
  "name": {
    "confidence": [
      1.0
    ],
    "excerpt": "RNN-LSTM-GRU_Tensorflow-HybridModel-ResidualGRUResNet-Toderici17-CVPR",
    "technique": "GitHub API"
  },
  "owner": {
    "confidence": [
      1.0
    ],
    "excerpt": "edmontdants",
    "technique": "GitHub API"
  },
  "ownerType": {
    "confidence": [
      1.0
    ],
    "excerpt": "User",
    "technique": "GitHub API"
  },
  "readme_url": {
    "confidence": [
      1.0
    ],
    "excerpt": "https://github.com/edmontdants/RNN-LSTM-GRU_Tensorflow-HybridModel-ResidualGRUResNet-Toderici17-CVPR/blob/main/README.md",
    "technique": "GitHub API"
  },
  "releases": {
    "confidence": [
      1.0
    ],
    "excerpt": [
      {
        "authorType": "User",
        "author_name": "edmontdants",
        "body": "Residual GRU Pretrained Compression based Model",
        "dateCreated": "2021-04-26T20:34:10Z",
        "datePublished": "2021-04-27T13:29:34Z",
        "html_url": "https://github.com/edmontdants/RNN-LSTM-GRU_Tensorflow-HybridModel-ResidualGRUResNet-Toderici17-CVPR/releases/tag/1.0",
        "name": "Trained Model",
        "tag_name": "1.0",
        "tarball_url": "https://api.github.com/repos/edmontdants/RNN-LSTM-GRU_Tensorflow-HybridModel-ResidualGRUResNet-Toderici17-CVPR/tarball/1.0",
        "url": "https://api.github.com/repos/edmontdants/RNN-LSTM-GRU_Tensorflow-HybridModel-ResidualGRUResNet-Toderici17-CVPR/releases/42072992",
        "zipball_url": "https://api.github.com/repos/edmontdants/RNN-LSTM-GRU_Tensorflow-HybridModel-ResidualGRUResNet-Toderici17-CVPR/zipball/1.0"
      }
    ],
    "technique": "GitHub API"
  },
  "requirement": [
    {
      "confidence": [
        1
      ],
      "excerpt": "* **GPU is not necessary** but preferable\n* like 4Gb of RAM\n\n",
      "technique": "Header extraction"
    },
    {
      "confidence": [
        1
      ],
      "excerpt": "The only software requirements for running the encoder and decoder is having Tensorflow installed.\nYou will also need to [download](https://drive.google.com/file/d/1nh4cxxds-BdsU0Tx3qP_cA1IuY2dDD5W) this compression based model [residual_gru.pb]\n\nIf you want to generate the perceptual similarity under MS-SSIM, you will also need to [Install SciPy](https://www.scipy.org/install.html).\n\n",
      "technique": "Header extraction"
    }
  ],
  "stargazers_count": {
    "confidence": [
      1.0
    ],
    "excerpt": {
      "count": 0,
      "date": "Thu, 23 Dec 2021 16:32:57 GMT"
    },
    "technique": "GitHub API"
  },
  "usage": [
    {
      "confidence": [
        1
      ],
      "excerpt": "This is usually due to the fact that the network only supports images that are\nboth height and width divisible by 32 pixel. Try padding your images to 32\npixel boundaries.\n\n\n",
      "technique": "Header extraction"
    }
  ]
}