{
  "citation": [
    {
      "confidence": [
        0.9998846322770001,
        0.9944484218006108
      ],
      "excerpt": "  Siyuan Qiao Huiyu Wang Chenxi Liu Wei Shen Alan Yuille : \u201cWeight Standardization\u201d (2019) \n  https://arxiv.org/pdf/1903.10520v1.pdf \n",
      "technique": "Supervised classification"
    }
  ],
  "codeRepository": {
    "confidence": [
      1.0
    ],
    "excerpt": "https://github.com/ThomasEhling/Weight_Standardization",
    "technique": "GitHub API"
  },
  "dateCreated": {
    "confidence": [
      1.0
    ],
    "excerpt": "2019-04-26T14:15:32Z",
    "technique": "GitHub API"
  },
  "dateModified": {
    "confidence": [
      1.0
    ],
    "excerpt": "2021-09-02T22:33:40Z",
    "technique": "GitHub API"
  },
  "description": [
    {
      "confidence": [
        0.9208232869510805,
        0.942118653808668
      ],
      "excerpt": "Weight Standardization Analysis with Keras \nWeight standardization is a new regularization technique that can outperform Batch Normalisation on micro batches, while reaching the same performance on large batches. \n",
      "technique": "Supervised classification"
    },
    {
      "confidence": [
        0.9336286697172373,
        0.8290097317593506,
        0.9624472846451537
      ],
      "excerpt": "We tested the performance of Group Normalization (GN) + Weight Standardization (WS) against Batch Normalization (BN) with a multiclass classifier on the MNIST-FASHION dataset. \nWe are using Python 3.6 and the Keras library. \nThe code for the original classifier is this official Google Example : \n",
      "technique": "Supervised classification"
    },
    {
      "confidence": [
        0.9086189798105265
      ],
      "excerpt": "To implement GN we used the code available at this repo : \n",
      "technique": "Supervised classification"
    },
    {
      "confidence": [
        0.8779314045975152
      ],
      "excerpt": "To implement WS we used a custom keras kernel regulizer funcitons : \n",
      "technique": "Supervised classification"
    },
    {
      "confidence": [
        0.8747974524448175
      ],
      "excerpt": "\"/src\" : source code, the python notebook is meant to be load in colab, with your drive mounted locallt? \n",
      "technique": "Supervised classification"
    },
    {
      "confidence": [
        1.0
      ],
      "excerpt": "Weight Standardization Analysis",
      "technique": "GitHub API"
    }
  ],
  "downloadUrl": {
    "confidence": [
      1.0
    ],
    "excerpt": "https://github.com/ThomasEhling/Weight_Standardization/releases",
    "technique": "GitHub API"
  },
  "forks_count": {
    "confidence": [
      1.0
    ],
    "excerpt": {
      "count": 1,
      "date": "Thu, 23 Dec 2021 22:04:39 GMT"
    },
    "technique": "GitHub API"
  },
  "forks_url": {
    "confidence": [
      1.0
    ],
    "excerpt": "https://api.github.com/repos/ThomasEhling/Weight_Standardization/forks",
    "technique": "GitHub API"
  },
  "fullName": {
    "confidence": [
      1.0
    ],
    "excerpt": "ThomasEhling/Weight_Standardization",
    "technique": "GitHub API"
  },
  "hasExecutableNotebook": {
    "confidence": [
      1.0
    ],
    "excerpt": [
      "https://raw.githubusercontent.com/ThomasEhling/Weight_Standardization/master/src/MNIST_Fashion_classifier.ipynb"
    ],
    "technique": "File Exploration"
  },
  "invocation": [
    {
      "confidence": [
        0.9368446689941579
      ],
      "excerpt": "  kernel_mean = tf.math.reduce_mean(kernel, axis=[0, 1, 2], keepdims=True, name='kernel_mean') \n",
      "technique": "Supervised classification"
    },
    {
      "confidence": [
        0.856799709112011
      ],
      "excerpt": "  kernel_std = tf.keras.backend.std(kernel, axis=[0, 1, 2], keepdims=True) \n",
      "technique": "Supervised classification"
    },
    {
      "confidence": [
        0.8276746414135452
      ],
      "excerpt": "Batch size | 2 | 64 | 128 \n",
      "technique": "Supervised classification"
    },
    {
      "confidence": [
        0.8526704960359491
      ],
      "excerpt": "The python code will run for a default batch size of 128 and 10 apochs. \n",
      "technique": "Supervised classification"
    }
  ],
  "issueTracker": {
    "confidence": [
      1.0
    ],
    "excerpt": "https://api.github.com/repos/ThomasEhling/Weight_Standardization/issues{/number}",
    "technique": "GitHub API"
  },
  "languages": {
    "confidence": [
      1.0
    ],
    "excerpt": [
      "Jupyter Notebook",
      "Python"
    ],
    "technique": "GitHub API"
  },
  "license": {
    "confidence": [
      1.0
    ],
    "technique": "GitHub API"
  },
  "long_title": {
    "confidence": [
      1.0
    ],
    "excerpt": "Weight_Standardization",
    "technique": "Regular expression"
  },
  "name": {
    "confidence": [
      1.0
    ],
    "excerpt": "Weight_Standardization",
    "technique": "GitHub API"
  },
  "owner": {
    "confidence": [
      1.0
    ],
    "excerpt": "ThomasEhling",
    "technique": "GitHub API"
  },
  "ownerType": {
    "confidence": [
      1.0
    ],
    "excerpt": "User",
    "technique": "GitHub API"
  },
  "readme_url": {
    "confidence": [
      1.0
    ],
    "excerpt": "https://github.com/ThomasEhling/Weight_Standardization/blob/master/README.md",
    "technique": "GitHub API"
  },
  "stargazers_count": {
    "confidence": [
      1.0
    ],
    "excerpt": {
      "count": 7,
      "date": "Thu, 23 Dec 2021 22:04:39 GMT"
    },
    "technique": "GitHub API"
  }
}