{
    "syntactic": [],
    "semantic": [
        "layered",
        "virtual resource",
        "computing resource",
        "resource information"
    ],
    "union": [
        "layered",
        "virtual resource",
        "computing resource",
        "resource information"
    ],
    "enhanced": [
        "software architecture patterns",
        "network virtualization",
        "virtual machines",
        "cloud computing",
        "information management",
        "resource discovery"
    ],
    "explanation": {
        "computing resource": [
            "resource",
            "resource resource"
        ],
        "virtual resource": [
            "resource",
            "resource resource"
        ],
        "resource information": [
            "resource",
            "resource resource"
        ],
        "layered": [
            "layer"
        ],
        "software architecture patterns": [
            "layer"
        ],
        "network virtualization": [
            "resource",
            "resource resource"
        ],
        "virtual machines": [
            "resource",
            "resource resource"
        ],
        "cloud computing": [
            "resource",
            "resource resource"
        ],
        "information management": [
            "resource",
            "resource resource"
        ],
        "resource discovery": [
            "resource",
            "resource resource"
        ]
    }
}