{
  "arxivLinks": {
    "confidence": [
      1.0
    ],
    "excerpt": [
      "https://arxiv.org/abs/1903.06586\n\nstructure:\n![pic](https://github.com/ChriXiang/Selective_Kernel_Keras/blob/master/image.png"
    ],
    "technique": "Regular expression"
  },
  "citation": [
    {
      "confidence": [
        0.9977994744046882
      ],
      "excerpt": "paper: https://arxiv.org/abs/1903.06586 \n",
      "technique": "Supervised classification"
    }
  ],
  "codeRepository": {
    "confidence": [
      1.0
    ],
    "excerpt": "https://github.com/ChriXiang/Selective_Kernel_Keras",
    "technique": "GitHub API"
  },
  "dateCreated": {
    "confidence": [
      1.0
    ],
    "excerpt": "2019-10-15T09:29:38Z",
    "technique": "GitHub API"
  },
  "dateModified": {
    "confidence": [
      1.0
    ],
    "excerpt": "2020-10-02T11:16:56Z",
    "technique": "GitHub API"
  },
  "description": [
    {
      "confidence": [
        0.9676006859442676
      ],
      "excerpt": "My keras implementation of selective kernel module with (3x3) and (5x5) two branches \n",
      "technique": "Supervised classification"
    },
    {
      "confidence": [
        1.0
      ],
      "excerpt": "My keras implementation of selective kernel moduler",
      "technique": "GitHub API"
    }
  ],
  "downloadUrl": {
    "confidence": [
      1.0
    ],
    "excerpt": "https://github.com/ChriXiang/Selective_Kernel_Keras/releases",
    "technique": "GitHub API"
  },
  "forks_count": {
    "confidence": [
      1.0
    ],
    "excerpt": {
      "count": 1,
      "date": "Tue, 28 Dec 2021 05:27:01 GMT"
    },
    "technique": "GitHub API"
  },
  "forks_url": {
    "confidence": [
      1.0
    ],
    "excerpt": "https://api.github.com/repos/ChriXiang/Selective_Kernel_Keras/forks",
    "technique": "GitHub API"
  },
  "fullName": {
    "confidence": [
      1.0
    ],
    "excerpt": "ChriXiang/Selective_Kernel_Keras",
    "technique": "GitHub API"
  },
  "issueTracker": {
    "confidence": [
      1.0
    ],
    "excerpt": "https://api.github.com/repos/ChriXiang/Selective_Kernel_Keras/issues{/number}",
    "technique": "GitHub API"
  },
  "languages": {
    "confidence": [
      1.0
    ],
    "excerpt": [
      "Python"
    ],
    "technique": "GitHub API"
  },
  "license": {
    "confidence": [
      1.0
    ],
    "technique": "GitHub API"
  },
  "long_title": {
    "confidence": [
      1.0
    ],
    "excerpt": "Selective_Kernel_Keras",
    "technique": "Regular expression"
  },
  "name": {
    "confidence": [
      1.0
    ],
    "excerpt": "Selective_Kernel_Keras",
    "technique": "GitHub API"
  },
  "owner": {
    "confidence": [
      1.0
    ],
    "excerpt": "ChriXiang",
    "technique": "GitHub API"
  },
  "ownerType": {
    "confidence": [
      1.0
    ],
    "excerpt": "User",
    "technique": "GitHub API"
  },
  "readme_url": {
    "confidence": [
      1.0
    ],
    "excerpt": "https://github.com/ChriXiang/Selective_Kernel_Keras/blob/master/README.md",
    "technique": "GitHub API"
  },
  "stargazers_count": {
    "confidence": [
      1.0
    ],
    "excerpt": {
      "count": 3,
      "date": "Tue, 28 Dec 2021 05:27:01 GMT"
    },
    "technique": "GitHub API"
  }
}