{
  "arxivLinks": {
    "confidence": [
      1.0
    ],
    "excerpt": [
      "https://arxiv.org/abs/2006.09662",
      "https://arxiv.org/abs/1912.06844",
      "https://arxiv.org/abs/2106.01722",
      "https://arxiv.org/abs/1703.03400",
      "https://arxiv.org/abs/1703.03400"
    ],
    "technique": "Regular expression"
  },
  "citation": [
    {
      "confidence": [
        1
      ],
      "excerpt": "```\n@misc{mulitdigitmnist,\n  author = {Sun, Shao-Hua},\n  title = {Multi-digit MNIST for Few-shot Learning},\n  year = {2019},\n  journal = {GitHub repository},\n  url = {https://github.com/shaohua0116/MultiDigitMNIST},\n}\n```\n\n",
      "technique": "Header extraction"
    },
    {
      "confidence": [
        1.0
      ],
      "excerpt": "@misc{mulitdigitmnist,\n  author = {Sun, Shao-Hua},\n  title = {Multi-digit MNIST for Few-shot Learning},\n  year = {2019},\n  journal = {GitHub repository},\n  url = {https://github.com/shaohua0116/MultiDigitMNIST},\n}",
      "technique": "Regular expression"
    },
    {
      "confidence": [
        0.8356013927728488
      ],
      "excerpt": "- meta batch size: 12 \n",
      "technique": "Supervised classification"
    }
  ],
  "codeRepository": {
    "confidence": [
      1.0
    ],
    "excerpt": "https://github.com/shaohua0116/MultiDigitMNIST",
    "technique": "GitHub API"
  },
  "dateCreated": {
    "confidence": [
      1.0
    ],
    "excerpt": "2019-05-04T23:00:32Z",
    "technique": "GitHub API"
  },
  "dateModified": {
    "confidence": [
      1.0
    ],
    "excerpt": "2021-12-28T04:11:03Z",
    "technique": "GitHub API"
  },
  "description": [
    {
      "confidence": [
        1
      ],
      "excerpt": "`Multi-digit MNIST` generator creates datasets consisting of handwritten digit images from [MNIST](http://yann.lecun.com/exdb/mnist/) for few-shot image classification and meta-learning. It simply samples images from MNIST dataset and put digits together to create images with multiple digits. It also creates training/validation/testing splits (64/20/16 classes for DoubleMNIST and 640/200/160 for TripleMNIST). \n\nYou can generate customized by following the cammands provided in [Usage](https://github.com/shaohua0116/MultiDigitMNIST#usage) to change the number of images in each class, the image size, etc. You can also download generated datasets from [Datasets](https://github.com/shaohua0116/MultiDigitMNIST#datasets).\n\nThis repository benchmarks the performance of **MAML** ([Model-Agnostic Meta-Learning for Fast Adaptation of Deep Networks](https://arxiv.org/abs/1703.03400)) using datasets created via the generation script in a variety of settings.\n\nSome examples of images from the datasets are as follows. \n\n- Double MNIST Datasets (100 classes: `00` to `99`)\n\n| **Class** | 10 | 48 | 59 | 62 | 73 |\n| :---: | :---: | :---: | :---: | :---: | :---: |\n| **Image** | ![](./asset/examples/10/0_10.png) ![](./asset/examples/10/1_10.png) ![](./asset/examples/10/2_10.png) ![](./asset/examples/10/3_10.png) | ![](./asset/examples/48/0_48.png) ![](./asset/examples/48/1_48.png) ![](./asset/examples/48/2_48.png) ![](./asset/examples/48/3_48.png)| ![](./asset/examples/59/0_59.png) ![](./asset/examples/59/1_59.png) ![](./asset/examples/59/2_59.png) ![](./asset/examples/59/3_59.png) | ![](./asset/examples/62/0_62.png) ![](./asset/examples/62/1_62.png) ![](./asset/examples/62/2_62.png) ![](./asset/examples/62/3_62.png) | ![](./asset/examples/73/0_73.png) ![](./asset/examples/73/1_73.png) ![](./asset/examples/73/2_73.png) ![](./asset/examples/73/3_73.png) | \n\n- Triple MNIST Datasets (1000 classes: `000` to `999`)\n\n| **Class** | 039 | 146 | 258 | 512 | 874 |\n| :---: | :---: | :---: | :---: | :---: | :---: |\n| **Image** | ![](./asset/examples/039/0_039.png) ![](./asset/examples/039/1_039.png) ![](./asset/examples/039/2_039.png) ![](./asset/examples/039/3_039.png) | ![](./asset/examples/146/0_146.png) ![](./asset/examples/146/1_146.png) ![](./asset/examples/146/2_146.png) ![](./asset/examples/146/3_146.png)| ![](./asset/examples/258/0_258.png) ![](./asset/examples/258/1_258.png) ![](./asset/examples/258/2_258.png) ![](./asset/examples/258/3_258.png) | ![](./asset/examples/512/0_512.png) ![](./asset/examples/512/1_512.png) ![](./asset/examples/512/2_512.png) ![](./asset/examples/512/3_512.png) | ![](./asset/examples/874/0_874.png) ![](./asset/examples/874/1_874.png) ![](./asset/examples/874/2_874.png) ![](./asset/examples/874/3_874.png) | \n\n",
      "technique": "Header extraction"
    },
    {
      "confidence": [
        0.8804161887487599
      ],
      "excerpt": "--image_size: the size of images. Note that the width needs to be larger than num_digit * mnist_width \n",
      "technique": "Supervised classification"
    },
    {
      "confidence": [
        0.9656327583530843
      ],
      "excerpt": "This repository benchmarks training MAML (Model-Agnostic Meta-Learning for Fast Adaptation of Deep Networks) using datasets created via this generation script in a variety of settings. \n",
      "technique": "Supervised classification"
    },
    {
      "confidence": [
        0.8094343176053485
      ],
      "excerpt": "*The trainings have not fully converged and the new results will be reported once they are finished. \n",
      "technique": "Supervised classification"
    },
    {
      "confidence": [
        1.0
      ],
      "excerpt": "Combine multiple MNIST digits to create datasets with 100/1000 classes for few-shot learning/meta-learning",
      "technique": "GitHub API"
    }
  ],
  "downloadUrl": {
    "confidence": [
      1.0
    ],
    "excerpt": "https://github.com/shaohua0116/MultiDigitMNIST/releases",
    "technique": "GitHub API"
  },
  "forks_count": {
    "confidence": [
      1.0
    ],
    "excerpt": {
      "count": 11,
      "date": "Thu, 30 Dec 2021 06:40:43 GMT"
    },
    "technique": "GitHub API"
  },
  "forks_url": {
    "confidence": [
      1.0
    ],
    "excerpt": "https://api.github.com/repos/shaohua0116/MultiDigitMNIST/forks",
    "technique": "GitHub API"
  },
  "fullName": {
    "confidence": [
      1.0
    ],
    "excerpt": "shaohua0116/MultiDigitMNIST",
    "technique": "GitHub API"
  },
  "installation": [
    {
      "confidence": [
        0.8620255736365737
      ],
      "excerpt": "You can download the generated datasets \n",
      "technique": "Supervised classification"
    }
  ],
  "invocation": [
    {
      "confidence": [
        0.9314622303483002
      ],
      "excerpt": "    <img src=\"asset/examples/multimnist_example.png\" weight=\"1024\"/> \n",
      "technique": "Supervised classification"
    },
    {
      "confidence": [
        0.8654892731161613
      ],
      "excerpt": "| Dataset | Image size | Train/Val/Test classes | \n",
      "technique": "Supervised classification"
    },
    {
      "confidence": [
        0.9171284688113023
      ],
      "excerpt": "    <img src=\"asset/training.png\" width=\"800\"/> \n",
      "technique": "Supervised classification"
    }
  ],
  "issueTracker": {
    "confidence": [
      1.0
    ],
    "excerpt": "https://api.github.com/repos/shaohua0116/MultiDigitMNIST/issues{/number}",
    "technique": "GitHub API"
  },
  "languages": {
    "confidence": [
      1.0
    ],
    "excerpt": [
      "Python"
    ],
    "technique": "GitHub API"
  },
  "license": {
    "confidence": [
      1.0
    ],
    "excerpt": {
      "name": "MIT License",
      "url": "https://api.github.com/licenses/mit"
    },
    "technique": "GitHub API"
  },
  "licenseText": {
    "confidence": [
      1.0
    ],
    "excerpt": "b'MIT License\\n\\nCopyright (c) 2019 Shao-Hua Sun\\n\\nPermission is hereby granted, free of charge, to any person obtaining a copy\\nof this software and associated documentation files (the \"Software\"), to deal\\nin the Software without restriction, including without limitation the rights\\nto use, copy, modify, merge, publish, distribute, sublicense, and/or sell\\ncopies of the Software, and to permit persons to whom the Software is\\nfurnished to do so, subject to the following conditions:\\n\\nThe above copyright notice and this permission notice shall be included in all\\ncopies or substantial portions of the Software.\\n\\nTHE SOFTWARE IS PROVIDED \"AS IS\", WITHOUT WARRANTY OF ANY KIND, EXPRESS OR\\nIMPLIED, INCLUDING BUT NOT LIMITED TO THE WARRANTIES OF MERCHANTABILITY,\\nFITNESS FOR A PARTICULAR PURPOSE AND NONINFRINGEMENT. IN NO EVENT SHALL THE\\nAUTHORS OR COPYRIGHT HOLDERS BE LIABLE FOR ANY CLAIM, DAMAGES OR OTHER\\nLIABILITY, WHETHER IN AN ACTION OF CONTRACT, TORT OR OTHERWISE, ARISING FROM,\\nOUT OF OR IN CONNECTION WITH THE SOFTWARE OR THE USE OR OTHER DEALINGS IN THE\\nSOFTWARE.\\n'",
    "technique": "File Exploration"
  },
  "long_title": {
    "confidence": [
      1.0
    ],
    "excerpt": "Multi-digit MNIST for Few-shot Learning",
    "technique": "Regular expression"
  },
  "name": {
    "confidence": [
      1.0
    ],
    "excerpt": "MultiDigitMNIST",
    "technique": "GitHub API"
  },
  "owner": {
    "confidence": [
      1.0
    ],
    "excerpt": "shaohua0116",
    "technique": "GitHub API"
  },
  "ownerType": {
    "confidence": [
      1.0
    ],
    "excerpt": "User",
    "technique": "GitHub API"
  },
  "readme_url": {
    "confidence": [
      1.0
    ],
    "excerpt": "https://github.com/shaohua0116/MultiDigitMNIST/blob/master/README.md",
    "technique": "GitHub API"
  },
  "requirement": [
    {
      "confidence": [
        1
      ],
      "excerpt": "- [NumPy](http://www.numpy.org/)\n- [imageio](https://pypi.org/project/imageio/)\n\n",
      "technique": "Header extraction"
    }
  ],
  "stargazers_count": {
    "confidence": [
      1.0
    ],
    "excerpt": {
      "count": 64,
      "date": "Thu, 30 Dec 2021 06:40:43 GMT"
    },
    "technique": "GitHub API"
  },
  "topics": {
    "confidence": [
      1.0
    ],
    "excerpt": [
      "few-shot-learning",
      "meta-learning",
      "image-classification",
      "mnist",
      "mnist-classification",
      "dataset"
    ],
    "technique": "GitHub API"
  },
  "usage": [
    {
      "confidence": [
        1
      ],
      "excerpt": "- MetaSDF: Meta-learning Signed Distance Functions (NeurIPS 2020): [Paper](https://arxiv.org/abs/2006.09662), [Project page](https://vsitzmann.github.io/metasdf/), [Code](https://github.com/vsitzmann/metasdf)\n- Regularizing Deep Multi-Task Networks using Orthogonal Gradients: [Paper](https://arxiv.org/abs/1912.06844)\n- GMAIR: Unsupervised Object Detection Based on Spatial Attention and Gaussian Mixture: [Paper](https://arxiv.org/abs/2106.01722)\n- Data-free meta learning via knowledge distillation from multiple teachers: [Thesis](https://epub.ub.uni-muenchen.de/75191/1/MA_Gruber_Sebastian.pdf)\n\n",
      "technique": "Header extraction"
    },
    {
      "confidence": [
        1
      ],
      "excerpt": "Generate a DoubleMNIST dataset with 1k images for each class\n\n```bash\npython generator.py --num_image_per_class 1000 --multimnist_path ./dataset/double_mnist --num_digit 2 --image_size 64 64\n```\n\nGenerate a TripleMNIST dataset with 1k images for each class\n\n```bash\npython generator.py --num_image_per_class 1000 --multimnist_path ./dataset/triple_mnist --num_digit 3 --image_size 84 84\n```\n\n",
      "technique": "Header extraction"
    }
  ]
}